mymlpackage/PCA.py
mymlpackage/__init__.py
mymlpackage/categorical_scatter.py
mymlpackage/k_means.py
mymlpackage/k_medoids.py
mymlpackage/svd.py
mymlpackage/t_sne.py
mymlpackage-1.0.2.dist-info/METADATA
mymlpackage-1.0.2.dist-info/WHEEL
mymlpackage-1.0.2.dist-info/top_level.txt
mymlpackage-1.0.2.dist-info/RECORD
