Metadata-Version: 2.1
Name: mymlpackage
Version: 1.0.2
Summary: A collection of minimal and clean implementations of machine learning algorithms.
Home-page: https://github.com/lmbd92/mymlpackage
Author: Lina Beltrán
Author-email: linam.beltran@udea.edu.co
License: MIT
